toggl/TogglPy.py
toggl/__init__.py
toggl/tests.py
toggl/toggl2gsuite.py
TogglPy-0.1.2.dist-info/LICENSE
TogglPy-0.1.2.dist-info/METADATA
TogglPy-0.1.2.dist-info/WHEEL
TogglPy-0.1.2.dist-info/top_level.txt
TogglPy-0.1.2.dist-info/RECORD
