Metadata-Version: 2.1
Name: TogglPy
Version: 0.1.2
Summary: Python library for interacting with the Toggl API.
Home-page: https://github.com/matthewdowney/TogglPy
Author: Matthew Downey
Author-email: matthewdowney20@gmail.com
License: MIT License
Keywords: api toggl
Platform: UNKNOWN
Classifier: Development Status :: 4 - Beta
Classifier: Intended Audience :: Developers
Classifier: License :: OSI Approved :: MIT License
Classifier: Natural Language :: English
Classifier: Programming Language :: Python
Classifier: Programming Language :: Python :: 2
Classifier: Programming Language :: Python :: 2.7
Classifier: Programming Language :: Python :: 3
Classifier: Programming Language :: Python :: 3.5
Classifier: Programming Language :: Python :: 3.6
Classifier: Programming Language :: Python :: 3.7
Classifier: Topic :: Software Development :: Libraries :: Python Modules
License-File: LICENSE
